artconsole/__init__.py
artconsole/drawings.py
artconsole/main.py
artconsole-1.0.8.dist-info/licenses/LICENSE
artconsole-1.0.8.dist-info/METADATA
artconsole-1.0.8.dist-info/WHEEL
artconsole-1.0.8.dist-info/top_level.txt
artconsole-1.0.8.dist-info/RECORD
