Metadata-Version: 2.4
Name: artconsole
Version: 1.0.8
Summary: 🚀 This is a library 📖 for outputting beautiful ASCII images 🏞️ to the console written in Python 🐍!
Home-page: https://github.com/dimamshirokov/artconsole
Author: Dima M. Shirokov
Author-email: D.Shirokov05@yandex.ru
Project-URL: GitHub, https://github.com/dimamshirokov
Classifier: Programming Language :: Python :: 3.11
Classifier: License :: OSI Approved :: MIT License
Classifier: Operating System :: OS Independent
Requires-Python: >=3.6
License-File: LICENSE
Dynamic: author
Dynamic: author-email
Dynamic: classifier
Dynamic: description
Dynamic: description-content-type
Dynamic: home-page
Dynamic: license-file
Dynamic: project-url
Dynamic: requires-python
Dynamic: summary
